{
  "parent": "minecraft:recipes/root",
  "rewards": {
    "recipes": [
      "tropicraft:cooked_ray_from_smoking"
    ]
  },
  "criteria": {
    "has_raw_ray": {
      "trigger": "minecraft:inventory_changed",
      "conditions": {
        "items": [
          {
            "items": [
              "tropicraft:raw_ray"
            ]
          }
        ]
      }
    },
    "has_the_recipe": {
      "trigger": "minecraft:recipe_unlocked",
      "conditions": {
        "recipe": "tropicraft:cooked_ray_from_smoking"
      }
    }
  },
  "requirements": [
    [
      "has_raw_ray",
      "has_the_recipe"
    ]
  ]
}