{
  "parent": "minecraft:recipes/root",
  "criteria": {
    "has_ores_manganese": {
      "conditions": {
        "items": [
          {
            "tag": "forge:ores/manganese"
          }
        ]
      },
      "trigger": "minecraft:inventory_changed"
    },
    "has_the_recipe": {
      "conditions": {
        "recipe": "tropicraft:manganese_ingot_from_ores_manganese_smelting"
      },
      "trigger": "minecraft:recipe_unlocked"
    }
  },
  "requirements": [
    [
      "has_ores_manganese",
      "has_the_recipe"
    ]
  ],
  "rewards": {
    "recipes": [
      "tropicraft:manganese_ingot_from_ores_manganese_smelting"
    ]
  }
}