{
  "credit": "Made with Blockbench",
  "parent": "block/block",
  "textures": {
    "particle": "#planks"
  },
  "elements": [
    {
      "name": "plank",
      "from": [0, 6, 1],
      "to": [16, 8, 7],
      "faces": {
        "north": {"uv": [0, 0, 16, 2], "texture": "#planks"},
        "east": {"uv": [5, 9, 11, 11], "texture": "#planks", "cullface": "east"},
        "south": {"uv": [0, 7, 16, 9], "texture": "#planks"},
        "west": {"uv": [5, 9, 11, 11], "texture": "#planks", "cullface": "west"},
        "up": {"uv": [0, 9, 16, 15], "texture": "#planks"},
        "down": {"uv": [0, 1, 16, 7], "texture": "#planks"}
      }
    },
    {
      "name": "support",
      "from": [6, 3, 0],
      "to": [10, 7, 16],
      "faces": {
        "north": {"uv": [12, 0, 16, 4], "texture": "#planks", "cullface": "north"},
        "east": {"uv": [0, 0, 16, 4], "texture": "#planks"},
        "south": {"uv": [0, 0, 4, 4], "texture": "#planks", "cullface": "south"},
        "west": {"uv": [0, 0, 16, 4], "texture": "#planks"},
        "up": {"uv": [6, 0, 10, 16], "texture": "#planks"},
        "down": {"uv": [6, 0, 10, 16], "texture": "#planks"}
      }
    },
    {
      "name": "plank",
      "from": [0, 6, 9],
      "to": [16, 8, 15],
      "faces": {
        "north": {"uv": [0, 14, 16, 16], "texture": "#planks"},
        "east": {"uv": [5, 9, 11, 11], "texture": "#planks", "cullface": "east"},
        "south": {"uv": [0, 7, 16, 9], "texture": "#planks"},
        "west": {"uv": [5, 9, 11, 11], "texture": "#planks", "cullface": "west"},
        "up": {"uv": [0, 1, 16, 7], "texture": "#planks"},
        "down": {"uv": [0, 9, 16, 15], "texture": "#planks"}
      }
    }
  ]
}
