{
  "type": "minecraft:entity",
  "pools": [
    {
      "rolls": {
        "min": 3.0,
        "max": 4.0,
        "type": "minecraft:uniform"
      },
      "entries": [
        {
          "type": "minecraft:item",
          "functions": [
            {
              "function": "minecraft:looting_enchant",
              "count": {
                "min": 0.0,
                "max": 0.33333334
              }
            }
          ],
          "name": "minecraft:slime_ball"
        }
      ]
    }
  ]
}